babymaycry/__init__.py
babymaycry/api.py
babymaycry-0.0.8.dist-info/METADATA
babymaycry-0.0.8.dist-info/WHEEL
babymaycry-0.0.8.dist-info/RECORD
