Metadata-Version: 2.1
Name: babymaycry
Version: 0.0.8
Summary: Baby cry detection
Author-email: hvppycoding <hvppycoding@gmail.com>
Classifier: Programming Language :: Python :: 3
Requires-Python: >=3.7
Requires-Dist: pyaudio
Requires-Dist: python-telegram-bot
